gps_toolkit_py-0.1.23.dist-info/licenses/LICENSE
gps_tools/__init__.py
gps_tools/calculations.py
gps_tools/converters.py
gps_tools/core.py
gps_tools/distance.py
gps_tools/unified_converter.py
gps_tools/utils/__init__.py
gps_tools/utils/validation.py
gps_toolkit_py-0.1.23.dist-info/METADATA
gps_toolkit_py-0.1.23.dist-info/WHEEL
gps_toolkit_py-0.1.23.dist-info/top_level.txt
gps_toolkit_py-0.1.23.dist-info/RECORD
