Metadata-Version: 2.4
Name: gps-toolkit-py
Version: 0.1.23
Summary: A Python package for working with GPS coordinates
Home-page: https://github.com/username/gps-toolkit-py
Author: GPS Tools Team
Author-email: example@example.com
License: MIT
Project-URL: Homepage, https://github.com/username/gps-toolkit-py
Project-URL: Bug Tracker, https://github.com/username/gps-toolkit-py/issues
Project-URL: Documentation, https://github.com/username/gps-toolkit-py/documentation
Keywords: gps,geospatial,coordinates,utm,mgrs
Classifier: Programming Language :: Python :: 3
Classifier: Programming Language :: Python :: 3.7
Classifier: Programming Language :: Python :: 3.8
Classifier: Programming Language :: Python :: 3.9
Classifier: Programming Language :: Python :: 3.10
Classifier: License :: OSI Approved :: MIT License
Classifier: Operating System :: OS Independent
Classifier: Topic :: Scientific/Engineering :: GIS
Classifier: Topic :: Software Development :: Libraries :: Python Modules
Requires-Python: >=3.7
License-File: LICENSE
Requires-Dist: numpy
Requires-Dist: scipy
Requires-Dist: pyproj
Provides-Extra: dev
Requires-Dist: pytest>=6.0; extra == "dev"
Requires-Dist: pytest-cov; extra == "dev"
Requires-Dist: black; extra == "dev"
Requires-Dist: flake8; extra == "dev"
Requires-Dist: mypy; extra == "dev"
Requires-Dist: pre-commit; extra == "dev"
Provides-Extra: viz
Requires-Dist: matplotlib; extra == "viz"
Requires-Dist: folium; extra == "viz"
Provides-Extra: gis
Requires-Dist: shapely; extra == "gis"
Requires-Dist: geopandas; extra == "gis"
Dynamic: author-email
Dynamic: home-page
Dynamic: license-file
Dynamic: requires-python
